nfdinspector/__init__.py
nfdinspector/__main__.py
nfdinspector/ead_inspector.py
nfdinspector/error.py
nfdinspector/lido_inspector.py
nfdinspector/metadata_inspector.py
NFDInspector-0.2.1.dist-info/LICENSE
NFDInspector-0.2.1.dist-info/METADATA
NFDInspector-0.2.1.dist-info/WHEEL
NFDInspector-0.2.1.dist-info/top_level.txt
NFDInspector-0.2.1.dist-info/RECORD
