Metadata-Version: 2.1
Name: NFDInspector
Version: 0.2.1
Summary: A Python package to inspect formal quality problems in research data.
Home-page: https://github.com/montan-code/nfdinspector
Author: Andreas Ketelaer
Author-email: Andreas Ketelaer <andreas.ketelaer@bergbaumuseum.de>
License: Copyright (c) 2024 Andreas Ketelaer
Project-URL: Homepage, https://github.com/montan-code/nfdinspector
Project-URL: Bug Tracker, https://github.com/montan-code/nfdinspector/issues
Classifier: License :: OSI Approved :: GNU General Public License v3 or later (GPLv3+)
Classifier: Programming Language :: Python
Classifier: Programming Language :: Python :: 3
Classifier: Programming Language :: Python :: 3.10
Classifier: Programming Language :: Python :: 3.11
Classifier: Programming Language :: Python :: 3.12
Classifier: Programming Language :: Python :: 3.13
Requires-Python: >=3.10
License-File: LICENSE
